{"js基础知识_2_10conditionalbranch.md":"13900c87","js基础知识_2_11logicaloperator.md":"57c1608f","js基础知识_2_12nullishcoalescing.md":"b13b0f3a","js基础知识_2_13circulation.md":"5925bf98","js基础知识_2_14switch.md":"e77ec723","js基础知识_2_15function.md":"27577298","js基础知识_2_16functionexpression.md":"94e89518","js基础知识_2_17arrowfunction.md":"e6157eb4","js基础知识_2_18jsspeciality.md":"2b81f68f","js基础知识_2_1helloworld.md":"cb15b287","js基础知识_2_2code-structure.md":"d25ec789","js基础知识_2_3use-strict.md":"951e32bf","js基础知识_2_4variate.md":"ee5d700e","js基础知识_2_5datatype.md":"7dd293a3","js基础知识_2_6interact.md":"42d821ac","js基础知识_2_7typecast.md":"65fde31a","js基础知识_2_8baseoperator.md":"a2cf37a3","js基础知识_2_9valuecomparison.md":"cead96ae","js简介_1_1introduction.md":"e2144cab","js简介_1_2standard.md":"a6b23d95","js简介_1_3code-editor.md":"ca6ebef2","js简介_1_4console.md":"fd89b9b2","object基础知识_4_1object.md":"bdd42170","object基础知识_4_2copy.md":"6499f0d6","object基础知识_4_3recycle.md":"0898eaab","object基础知识_4_4method.md":"426529f3","object基础知识_4_5constructor.md":"a8967c6b","object基础知识_4_6optionalchain.md":"dbfcba97","object基础知识_4_7symbol.md":"e338f82b","object基础知识_4_8valueconversion.md":"9d44e267","index.md":"81317cd7","代码质量_3_1debug.md":"e122018c","代码质量_3_2codestyle.md":"9eb634f3","代码质量_3_3annotation.md":"91a1180f","代码质量_3_4ninjacode.md":"53f59e63","代码质量_3_5mocha.md":"49cfd71f","代码质量_3_6polyfill.md":"72c4862d","函数进阶内容_6_10funcbind.md":"f4f1db56","函数进阶内容_6_11arrowfunction.md":"1b4ec6c4","函数进阶内容_6_1recursion.md":"e1e2692e","函数进阶内容_6_2rest.md":"e9e551d8","函数进阶内容_6_3closure.md":"14bf1c9b","函数进阶内容_6_4var.md":"2f67e39c","函数进阶内容_6_5globalobject.md":"397786fc","函数进阶内容_6_6funcobj.md":"f6afa557","函数进阶内容_6_7newfunc.md":"144cc564","函数进阶内容_6_8dispatch.md":"996a3368","函数进阶内容_6_9decorator.md":"6774f9ed","对象属性配置_7_1attributetag.md":"0eff31ae","对象属性配置_7_2getter.md":"97b685da","数据类型_5_10destructuring.md":"2b7b7445","数据类型_5_11date.md":"b86affa9","数据类型_5_12json.md":"f6821a27","数据类型_5_1primitivetypemethods.md":"c13ae72d","数据类型_5_2numbertype.md":"7a9b5ba8","数据类型_5_3string.md":"2f3439b8","数据类型_5_4array.md":"298280ad","数据类型_5_5arraymethod.md":"b2d21121","数据类型_5_6iterableobject.md":"ffff5bce","数据类型_5_7mapset.md":"04446feb","数据类型_5_8weakmapweakset.md":"94d5ddc9","数据类型_5_9objectkeys.md":"dd2cb2dd"}
